budgetcli/__init__.py
budgetcli/ai_chatting.py
budgetcli/cli.py
budgetcli/file_io.py
budgetcli/main.py
budgetcli/utils.py
budgetingcli-0.1.2.dist-info/METADATA
budgetingcli-0.1.2.dist-info/WHEEL
budgetingcli-0.1.2.dist-info/entry_points.txt
budgetingcli-0.1.2.dist-info/top_level.txt
budgetingcli-0.1.2.dist-info/RECORD
