Metadata-Version: 2.1
Name: budgetingcli
Version: 0.1.2
Summary: A CLI tool to track spending goals and habits
Home-page: https://github.com/shmurthy08/budgetingCLI
Author: Shree Murthy
Requires-Python: >=3.8
Requires-Dist: click
Requires-Dist: rich
Requires-Dist: ollama
Requires-Dist: platformdirs
